avikus_response/__init__.py
avikus_response/model.py
avikus_response/response.py
standard_response_lib-0.0.5.dist-info/LICENSE
standard_response_lib-0.0.5.dist-info/METADATA
standard_response_lib-0.0.5.dist-info/WHEEL
standard_response_lib-0.0.5.dist-info/top_level.txt
standard_response_lib-0.0.5.dist-info/RECORD
