Metadata-Version: 2.1
Name: standard-response-lib
Version: 0.0.5
Summary: A response library package
Home-page: https://github.com/avikus-ai/standard-response-lib
Author: Avikus
Author-email: dev@avikus.ai
License: UNKNOWN
Platform: UNKNOWN
Classifier: Programming Language :: Python :: 3
Classifier: License :: OSI Approved :: MIT License
Classifier: Operating System :: OS Independent
Requires-Python: >=3.8
License-File: LICENSE
Requires-Dist: pydantic (>=1.10.2)
